stimpyp/__init__.py
stimpyp/_type.py
stimpyp/_util.py
stimpyp/base.py
stimpyp/camlog.py
stimpyp/event.py
stimpyp/log_config.py
stimpyp/math_eval.py
stimpyp/plot.py
stimpyp/preference.py
stimpyp/protocol_parser.py
stimpyp/pyvstim.py
stimpyp/session.py
stimpyp/stimpy_core.py
stimpyp/stimpy_git.py
stimpyp/stimpy_pygame.py
stimpyp/stimulus.py
stimpyp-0.3.3.dist-info/licenses/LICENSE
stimpyp-0.3.3.dist-info/METADATA
stimpyp-0.3.3.dist-info/WHEEL
stimpyp-0.3.3.dist-info/top_level.txt
stimpyp-0.3.3.dist-info/RECORD
