Metadata-Version: 2.4
Name: stimpyp
Version: 0.3.3
Summary: utilities parser for the Stimpy module
Author-email: Yu-Ting Wei <ytsimon2004@gmail.com>
License: BSD 3-Clause License
Project-URL: Homepage, https://github.com/ytsimon2004/stimpyp
Project-URL: Documentation, https://neuralib.readthedocs.io/en/latest/index.html
Project-URL: Repository, https://github.com/ytsimon2004/stimpyp
Project-URL: Issues, https://github.com/ytsimon2004/stimpyp/issues
Keywords: Neuroscience,visual neuroscience,virtual reality
Classifier: Programming Language :: Python :: 3.10
Classifier: License :: OSI Approved :: BSD License
Classifier: Natural Language :: English
Classifier: Operating System :: OS Independent
Classifier: Topic :: Scientific/Engineering
Classifier: Intended Audience :: Science/Research
Classifier: Typing :: Typed
Requires-Python: >=3.10
License-File: LICENSE
Requires-Dist: attrs
Requires-Dist: numpy
Requires-Dist: scipy
Requires-Dist: pandas
Requires-Dist: polars
Requires-Dist: pyarrow
Requires-Dist: pyparsing
Requires-Dist: rich
Requires-Dist: matplotlib
Requires-Dist: typing_extensions
Provides-Extra: dev
Requires-Dist: gdown; extra == "dev"
Provides-Extra: doc
Requires-Dist: sphinx; extra == "doc"
Requires-Dist: pydata-sphinx-theme; extra == "doc"
Requires-Dist: sphinx_prompt; extra == "doc"
Requires-Dist: sphinx_copybutton; extra == "doc"
Requires-Dist: sphinx-toolbox; extra == "doc"
Dynamic: license-file
